autogluon.tabular-1.4.0-py3.9-nspkg.pth
autogluon/tabular/__init__.py
autogluon/tabular/version.py
autogluon/tabular/configs/__init__.py
autogluon/tabular/configs/config_helper.py
autogluon/tabular/configs/feature_generator_presets.py
autogluon/tabular/configs/hyperparameter_configs.py
autogluon/tabular/configs/presets_configs.py
autogluon/tabular/configs/zeroshot/__init__.py
autogluon/tabular/configs/zeroshot/zeroshot_portfolio_2023.py
autogluon/tabular/configs/zeroshot/zeroshot_portfolio_2025.py
autogluon/tabular/experimental/__init__.py
autogluon/tabular/experimental/_scikit_mixin.py
autogluon/tabular/experimental/_tabular_classifier.py
autogluon/tabular/experimental/_tabular_regressor.py
autogluon/tabular/experimental/plot_leaderboard.py
autogluon/tabular/learner/__init__.py
autogluon/tabular/learner/abstract_learner.py
autogluon/tabular/learner/default_learner.py
autogluon/tabular/models/__init__.py
autogluon/tabular/models/_utils/__init__.py
autogluon/tabular/models/_utils/rapids_utils.py
autogluon/tabular/models/_utils/torch_utils.py
autogluon/tabular/models/automm/__init__.py
autogluon/tabular/models/automm/automm_model.py
autogluon/tabular/models/automm/ft_transformer.py
autogluon/tabular/models/catboost/__init__.py
autogluon/tabular/models/catboost/callbacks.py
autogluon/tabular/models/catboost/catboost_model.py
autogluon/tabular/models/catboost/catboost_softclass_utils.py
autogluon/tabular/models/catboost/catboost_utils.py
autogluon/tabular/models/catboost/hyperparameters/__init__.py
autogluon/tabular/models/catboost/hyperparameters/parameters.py
autogluon/tabular/models/catboost/hyperparameters/searchspaces.py
autogluon/tabular/models/fastainn/__init__.py
autogluon/tabular/models/fastainn/callbacks.py
autogluon/tabular/models/fastainn/fastai_helpers.py
autogluon/tabular/models/fastainn/imports_helper.py
autogluon/tabular/models/fastainn/quantile_helpers.py
autogluon/tabular/models/fastainn/tabular_nn_fastai.py
autogluon.tabular-1.4.0.dist-info/LICENSE
autogluon.tabular-1.4.0.dist-info/METADATA
autogluon.tabular-1.4.0.dist-info/NOTICE
autogluon.tabular-1.4.0.dist-info/WHEEL
autogluon.tabular-1.4.0.dist-info/namespace_packages.txt
autogluon.tabular-1.4.0.dist-info/top_level.txt
autogluon.tabular-1.4.0.dist-info/zip-safe
autogluon.tabular-1.4.0.dist-info/RECORD
