Metadata-Version: 2.1
Name: autogluon.tabular
Version: 1.4.0
Summary: Fast and Accurate ML in 3 Lines of Code
Home-page: https://github.com/autogluon/autogluon
Author: AutoGluon Community
License: Apache-2.0
Project-URL: Documentation, https://auto.gluon.ai
Project-URL: Bug Reports, https://github.com/autogluon/autogluon/issues
Project-URL: Source, https://github.com/autogluon/autogluon/
Project-URL: Contribute!, https://github.com/autogluon/autogluon/blob/master/CONTRIBUTING.md
Platform: UNKNOWN
Classifier: Development Status :: 5 - Production/Stable
Classifier: Intended Audience :: Education
Classifier: Intended Audience :: Developers
Classifier: Intended Audience :: Science/Research
Classifier: Intended Audience :: Customer Service
Classifier: Intended Audience :: Financial and Insurance Industry
Classifier: Intended Audience :: Healthcare Industry
Classifier: Intended Audience :: Telecommunications Industry
Classifier: License :: OSI Approved :: Apache Software License
Classifier: Operating System :: MacOS
Classifier: Operating System :: Microsoft :: Windows
Classifier: Operating System :: POSIX
Classifier: Operating System :: Unix
Classifier: Programming Language :: Python :: 3
Classifier: Programming Language :: Python :: 3.9
Classifier: Programming Language :: Python :: 3.10
Classifier: Programming Language :: Python :: 3.11
Classifier: Programming Language :: Python :: 3.12
Classifier: Topic :: Software Development
Classifier: Topic :: Scientific/Engineering :: Artificial Intelligence
Classifier: Topic :: Scientific/Engineering :: Information Analysis
Classifier: Topic :: Scientific/Engineering :: Image Recognition
Requires-Python: >=3.9, <3.13
License-File: ../LICENSE
License-File: ../NOTICE
Requires-Dist: numpy<2.4.0,>=1.25.0
Requires-Dist: scipy<1.17,>=1.5.4
Requires-Dist: pandas<2.4.0,>=2.0.0
Requires-Dist: scikit-learn<1.8.0,>=1.4.0
Requires-Dist: networkx<4,>=3.0
Requires-Dist: autogluon.core==1.4.0
Requires-Dist: autogluon.features==1.4.0
Provides-Extra: all
Requires-Dist: catboost<1.3,>=1.2; extra == "all"
Requires-Dist: fastai<2.9,>=2.3.1; extra == "all"
Requires-Dist: numpy<2.3.0,>=1.25; extra == "all"
Requires-Dist: loguru; extra == "all"
Requires-Dist: lightgbm<4.7,>=4.0; extra == "all"
Requires-Dist: einx; extra == "all"
Requires-Dist: autogluon.core[all]==1.4.0; extra == "all"
Requires-Dist: xgboost<3.1,>=2.0; extra == "all"
Requires-Dist: transformers; extra == "all"
Requires-Dist: spacy<3.9; extra == "all"
Requires-Dist: torch<2.8,>=2.2; extra == "all"
Requires-Dist: omegaconf; extra == "all"
Requires-Dist: huggingface-hub[torch]; extra == "all"
Requires-Dist: blis<1.2.1,>=0.7.0; (platform_system == "Windows" and python_version == "3.9") and extra == "all"
Provides-Extra: catboost
Requires-Dist: numpy<2.3.0,>=1.25; extra == "catboost"
Requires-Dist: catboost<1.3,>=1.2; extra == "catboost"
Provides-Extra: fastai
Requires-Dist: spacy<3.9; extra == "fastai"
Requires-Dist: torch<2.8,>=2.2; extra == "fastai"
Requires-Dist: fastai<2.9,>=2.3.1; extra == "fastai"
Requires-Dist: blis<1.2.1,>=0.7.0; (platform_system == "Windows" and python_version == "3.9") and extra == "fastai"
Provides-Extra: imodels
Requires-Dist: imodels<2.1.0,>=1.3.10; extra == "imodels"
Provides-Extra: lightgbm
Requires-Dist: lightgbm<4.7,>=4.0; extra == "lightgbm"
Provides-Extra: mitra
Requires-Dist: loguru; extra == "mitra"
Requires-Dist: einx; extra == "mitra"
Requires-Dist: omegaconf; extra == "mitra"
Requires-Dist: torch<2.8,>=2.2; extra == "mitra"
Requires-Dist: transformers; extra == "mitra"
Requires-Dist: huggingface-hub[torch]; extra == "mitra"
Provides-Extra: ray
Requires-Dist: autogluon.core[all]==1.4.0; extra == "ray"
Provides-Extra: realmlp
Requires-Dist: pytabkit<1.7,>=1.6; extra == "realmlp"
Provides-Extra: skex
Requires-Dist: scikit-learn-intelex<2025.5,>=2024.0; extra == "skex"
Provides-Extra: skl2onnx
Requires-Dist: skl2onnx<1.18.0,>=1.15.0; extra == "skl2onnx"
Requires-Dist: onnxruntime<1.20.0,>=1.17.0; extra == "skl2onnx"
Requires-Dist: onnxruntime-gpu<1.20.0,>=1.17.0; extra == "skl2onnx"
Requires-Dist: onnx<1.18.0,>=1.13.0; platform_system != "Windows" and extra == "skl2onnx"
Requires-Dist: onnx<1.16.2,>=1.13.0; platform_system == "Windows" and extra == "skl2onnx"
Provides-Extra: tabarena
Requires-Dist: catboost<1.3,>=1.2; extra == "tabarena"
Requires-Dist: fastai<2.9,>=2.3.1; extra == "tabarena"
Requires-Dist: numpy<2.3.0,>=1.25; extra == "tabarena"
Requires-Dist: loguru; extra == "tabarena"
Requires-Dist: lightgbm<4.7,>=4.0; extra == "tabarena"
Requires-Dist: einx; extra == "tabarena"
Requires-Dist: autogluon.core[all]==1.4.0; extra == "tabarena"
Requires-Dist: tabicl<0.2,>=0.1.3; extra == "tabarena"
Requires-Dist: xgboost<3.1,>=2.0; extra == "tabarena"
Requires-Dist: transformers; extra == "tabarena"
Requires-Dist: spacy<3.9; extra == "tabarena"
Requires-Dist: torch<2.8,>=2.2; extra == "tabarena"
Requires-Dist: omegaconf; extra == "tabarena"
Requires-Dist: huggingface-hub[torch]; extra == "tabarena"
Requires-Dist: tabpfn<2.2,>=2.0.9; extra == "tabarena"
Requires-Dist: pytabkit<1.7,>=1.6; extra == "tabarena"
Requires-Dist: blis<1.2.1,>=0.7.0; (platform_system == "Windows" and python_version == "3.9") and extra == "tabarena"
Provides-Extra: tabicl
Requires-Dist: tabicl<0.2,>=0.1.3; extra == "tabicl"
Provides-Extra: tabm
Requires-Dist: torch<2.8,>=2.2; extra == "tabm"
Provides-Extra: tabpfn
Requires-Dist: tabpfn<2.2,>=2.0.9; extra == "tabpfn"
Provides-Extra: tabpfnmix
Requires-Dist: torch<2.8,>=2.2; extra == "tabpfnmix"
Requires-Dist: huggingface-hub[torch]; extra == "tabpfnmix"
Requires-Dist: einops<0.9,>=0.7; extra == "tabpfnmix"
Provides-Extra: tests
Requires-Dist: tabicl<0.2,>=0.1.3; extra == "tests"
Requires-Dist: tabpfn<2.2,>=2.0.9; extra == "tests"
Requires-Dist: pytabkit<1.7,>=1.6; extra == "tests"
Requires-Dist: torch<2.8,>=2.2; extra == "tests"
Requires-Dist: huggingface-hub[torch]; extra == "tests"
Requires-Dist: einops<0.9,>=0.7; extra == "tests"
Requires-Dist: imodels<2.1.0,>=1.3.10; extra == "tests"
Requires-Dist: skl2onnx<1.18.0,>=1.15.0; extra == "tests"
Requires-Dist: onnxruntime<1.20.0,>=1.17.0; extra == "tests"
Requires-Dist: onnxruntime-gpu<1.20.0,>=1.17.0; extra == "tests"
Requires-Dist: onnx<1.18.0,>=1.13.0; platform_system != "Windows" and extra == "tests"
Requires-Dist: onnx<1.16.2,>=1.13.0; platform_system == "Windows" and extra == "tests"
Provides-Extra: xgboost
Requires-Dist: xgboost<3.1,>=2.0; extra == "xgboost"
